plyra/__init__.py
plyra/_additional_updates.py
plyra/_base.py
plyra/_themes.py
plyra-0.1.1.dist-info/licenses/LICENSE
plyra-0.1.1.dist-info/METADATA
plyra-0.1.1.dist-info/WHEEL
plyra-0.1.1.dist-info/top_level.txt
plyra-0.1.1.dist-info/RECORD
